arpifs_listings/TLAD.py
arpifs_listings/__init__.py
arpifs_listings/cost_functions.py
arpifs_listings/jo_tables.py
arpifs_listings/listings.py
arpifs_listings/norms.py
arpifs_listings/util.py
arpifs_listings/entrypoints/__init__.py
arpifs_listings/entrypoints/compare_listings.py
arpifis_listings-1.2.0b1.dist-info/LICENSE-en.txt
arpifis_listings-1.2.0b1.dist-info/LICENSE.txt
arpifis_listings-1.2.0b1.dist-info/METADATA
arpifis_listings-1.2.0b1.dist-info/WHEEL
arpifis_listings-1.2.0b1.dist-info/entry_points.txt
arpifis_listings-1.2.0b1.dist-info/top_level.txt
arpifis_listings-1.2.0b1.dist-info/RECORD
